slack_read_only_bot.py
slack_read_only_bot-1.0.0.dist-info/METADATA
slack_read_only_bot-1.0.0.dist-info/WHEEL
slack_read_only_bot-1.0.0.dist-info/entry_points.txt
slack_read_only_bot-1.0.0.dist-info/top_level.txt
slack_read_only_bot-1.0.0.dist-info/RECORD
