Metadata-Version: 2.1
Name: slack-read-only-bot
Version: 1.0.0
Summary: Make Slack channels read-only by restricting which users can post to them
Home-page: https://github.com/pR0Ps/slack-read-only-bot
License: GPLv3
Platform: UNKNOWN
Classifier: Programming Language :: Python :: 3
Classifier: Operating System :: OS Independent
Classifier: Topic :: Communications :: Chat
Classifier: License :: OSI Approved :: GNU General Public License v3 (GPLv3)
Requires-Python: >=3.6,<4
Requires-Dist: slackclient (<2.0.0,>=1.1.0)
Requires-Dist: pyyaml (<7.0.0,>=5.4.1)
